rkttravelbento/__init__.py
rkttravelbento/__main__.py
rkttravelbento-0.1.1.dist-info/WHEEL
rkttravelbento-0.1.1.dist-info/METADATA
rkttravelbento-0.1.1.dist-info/RECORD
