Metadata-Version: 2.1
Name: rkttravelbento
Version: 0.1.1
Summary: bento for customers
Author: siva
Author-email: sivakon@outlook.com
Requires-Python: >=3.7,<4.0
Classifier: Programming Language :: Python :: 3
Classifier: Programming Language :: Python :: 3.7
Requires-Dist: numpy (>=1.17,<2.0)
